<?xml version="1.0" encoding="UTF-8"?>
<Defs>
    
    <IncidentDef>
        <defName>NothingThereEmergence</defName>
        <label>nothing there</label>
        <category>Special</category>
        <target_Tags>
            <li>Map_PlayerHome</li>
        </target_Tags>
        <minAnomalyThreatLevel>2</minAnomalyThreatLevel>
        <workerClass>IncidentWorker_NothingThere</workerClass>
        <questScriptDef>NothingThereEmergence</questScriptDef>
        <letterLabel>Abnomaly attack</letterLabel>
        <letterText>(text)</letterText>
        <letterTextPlural>(spectific text)</letterTextPlural>
        <category>ThreatBig</category>
    </IncidentDef>
</Defs>